[{"line":2,"elements":[{"line":4,"name":"","description":"","type":"background","keyword":"Background","steps":[]},{"start_timestamp":"2023-08-21T17:03:31.876Z","before":[{"result":{"duration":3960326000,"status":"passed"},"match":{"location":"support.Hooks.scenarioStart()"}}],"line":109,"name":"Verify Total number of Questions in in \"My Assignments\" Panel","description":"","id":"quiz-total-questions-polina-sv;verify-total-number-of-questions-in-in-\"my-assignments\"-panel","after":[{"result":{"duration":380880900,"status":"passed"},"match":{"location":"support.Hooks.scenarioEnd(io.cucumber.java.Scenario)"}}],"type":"scenario","keyword":"Scenario","steps":[{"result":{"duration":872664400,"status":"passed"},"line":110,"name":"I open \"login\" page ps","match":{"arguments":[{"val":"\"login\"","offset":7}],"location":"definitions.QuizTotalQuestonsPSvStepDefs.iOpenPagePs(java.lang.String)"},"keyword":"Given "},{"result":{"duration":145610600,"status":"passed"},"line":111,"name":"I type \"burghboy@chcial.com\" into \"email\" field ps","match":{"arguments":[{"val":"\"burghboy@chcial.com\"","offset":7},{"val":"\"email\"","offset":34}],"location":"definitions.QuizTotalQuestonsPSvStepDefs.iTypeIntoFieldPs(java.lang.String,java.lang.String)"},"keyword":"When "},{"result":{"duration":107711500,"status":"passed"},"line":112,"name":"I type \"qwe123\" into \"password\" field ps","match":{"arguments":[{"val":"\"qwe123\"","offset":7},{"val":"\"password\"","offset":21}],"location":"definitions.QuizTotalQuestonsPSvStepDefs.iTypeIntoFieldPs(java.lang.String,java.lang.String)"},"keyword":"And "},{"result":{"duration":98736600,"status":"passed"},"line":113,"name":"I click \"Sign In\" button ps","match":{"arguments":[{"val":"\"Sign In\"","offset":8}],"location":"definitions.QuizTotalQuestonsPSvStepDefs.iClickButtonPs(java.lang.String)"},"keyword":"And "},{"result":{"duration":1007638300,"status":"passed"},"line":114,"name":"I wait for 1 sec ps","match":{"arguments":[{"val":"1","offset":11}],"location":"definitions.QuizTotalQuestonsPSvStepDefs.iWaitForSecPs(int)"},"keyword":"And "},{"result":{"duration":80363700,"status":"passed"},"line":115,"name":"I click \"My Assignments\" menu item ps","match":{"arguments":[{"val":"\"My Assignments\"","offset":8}],"location":"definitions.QuizTotalQuestonsPSvStepDefs.iClickMenuItemPs(java.lang.String)"},"keyword":"When "},{"result":{"duration":1005617600,"status":"passed"},"line":116,"name":"I wait for 1 sec ps","match":{"arguments":[{"val":"1","offset":11}],"location":"definitions.QuizTotalQuestonsPSvStepDefs.iWaitForSecPs(int)"},"keyword":"And "},{"result":{"duration":106021700,"status":"passed"},"line":117,"name":"\"ABC\" assignment should contain \"3\" questions ps","match":{"arguments":[{"val":"\"ABC\"","offset":0},{"val":"\"3\"","offset":32}],"location":"definitions.QuizTotalQuestonsPSvStepDefs.assignmentShouldContainQuestionsPs(java.lang.String,java.lang.String)"},"keyword":"Then "}],"tags":[{"name":"@quizTotalQuestionsPolinaSv"},{"name":"@TotalNumberOfQuestionsInMyAssignments"}]}],"name":"Quiz Total Questions Polina Sv","description":"","id":"quiz-total-questions-polina-sv","keyword":"Feature","uri":"file:src/test/resources/features/quiz_total_questions_polina_sv.feature","tags":[{"name":"@quizTotalQuestionsPolinaSv","type":"Tag","location":{"line":1,"column":1}}]}]