[{"line":2,"elements":[{"line":4,"name":": : Create a quiz","description":"","type":"background","keyword":"Background","steps":[{"result":{"duration":1067785000,"status":"passed"},"line":5,"name":"I open \"login\" page","match":{"arguments":[{"val":"\"login\"","offset":7}],"location":"definitions.SingleChoiceOptionStepDefs.iOpenPage(java.lang.String)"},"keyword":"Given "},{"result":{"duration":84392000,"status":"passed"},"line":6,"name":"I type \"coleverde@jucky.net\" into email field","match":{"arguments":[{"val":"\"coleverde@jucky.net\"","offset":7}],"location":"definitions.SingleChoiceOptionStepDefs.iTypeIntoEmailField(java.lang.String)"},"keyword":"When "},{"result":{"duration":28956000,"status":"passed"},"line":7,"name":"I type \"Intel2\" into password field","match":{"arguments":[{"val":"\"Intel2\"","offset":7}],"location":"definitions.SingleChoiceOptionStepDefs.iTypeIntoPasswordField(java.lang.String)"},"keyword":"When "},{"result":{"duration":28396000,"status":"passed"},"line":8,"name":"I click \"Sign In\" button","match":{"arguments":[{"val":"\"Sign In\"","offset":8}],"location":"definitions.SingleChoiceOptionStepDefs.iClickButton(java.lang.String)"},"keyword":"And "},{"result":{"duration":1004040000,"status":"passed"},"line":9,"name":"I wait for 1 sec","match":{"arguments":[{"val":"1","offset":11}],"location":"definitions.SingleChoiceOptionStepDefs.iWaitForSec(int)"},"keyword":"And "},{"result":{"duration":43017000,"status":"passed"},"line":10,"name":"I click \"Quizzes\" menu item","match":{"arguments":[{"val":"\"Quizzes\"","offset":8}],"location":"definitions.SingleChoiceOptionStepDefs.iClickMenuItem(java.lang.String)"},"keyword":"When "},{"result":{"duration":1005269000,"status":"passed"},"line":11,"name":"I wait for 1 sec","match":{"arguments":[{"val":"1","offset":11}],"location":"definitions.SingleChoiceOptionStepDefs.iWaitForSec(int)"},"keyword":"And "},{"result":{"duration":68189000,"status":"passed"},"line":12,"name":"I click \"Create New Quiz\" button","match":{"arguments":[{"val":"\"Create New Quiz\"","offset":8}],"location":"definitions.SingleChoiceOptionStepDefs.iClickButton(java.lang.String)"},"keyword":"And "},{"result":{"duration":1005175000,"status":"passed"},"line":13,"name":"I wait for 1 sec","match":{"arguments":[{"val":"1","offset":11}],"location":"definitions.SingleChoiceOptionStepDefs.iWaitForSec(int)"},"keyword":"And "},{"result":{"duration":54829000,"status":"passed"},"line":14,"name":"I type \"Title#\" as quiz name","match":{"arguments":[{"val":"\"Title#\"","offset":7}],"location":"definitions.SingleChoiceOptionStepDefs.iTypeQuizName(java.lang.String)"},"keyword":"And "},{"result":{"duration":33239000,"status":"passed"},"line":15,"name":"I add a question","match":{"location":"definitions.SingleChoiceOptionStepDefs.iAddAQuestion()"},"keyword":"And "},{"result":{"duration":3002436000,"status":"passed"},"line":16,"name":"I wait for 3 sec","match":{"arguments":[{"val":"3","offset":11}],"location":"definitions.SingleChoiceOptionStepDefs.iWaitForSec(int)"},"keyword":"And "},{"result":{"duration":61288000,"status":"passed"},"line":17,"name":"I select \"Single\" question","match":{"arguments":[{"val":"\"Single\"","offset":9}],"location":"definitions.SingleChoiceOptionStepDefs.iSelectQuestion(java.lang.String)"},"keyword":"When "},{"result":{"duration":2002970000,"status":"passed"},"line":18,"name":"I wait for 2 sec","match":{"arguments":[{"val":"2","offset":11}],"location":"definitions.SingleChoiceOptionStepDefs.iWaitForSec(int)"},"keyword":"And "}]},{"start_timestamp":"2023-08-21T15:07:45.765Z","before":[{"result":{"duration":1577855000,"status":"passed"},"match":{"location":"support.Hooks.scenarioStart()"}}],"line":154,"name":"Single Choice Question - Options with max (1000) ch-rs","description":"","id":"single-choice-question---options;single-choice-question---options-with-max-(1000)-ch-rs","after":[{"result":{"duration":106530000,"status":"passed"},"match":{"location":"support.Hooks.scenarioEnd(io.cucumber.java.Scenario)"}}],"type":"scenario","keyword":"Scenario","steps":[{"result":{"duration":56239000,"status":"passed"},"line":155,"name":"I type \"Question 1\" into question field of \"Q1\"","match":{"arguments":[{"val":"\"Question 1\"","offset":7},{"val":"\"Q1\"","offset":43}],"location":"definitions.SingleChoiceOptionStepDefs.iTypeIntoQuestionFieldOf(java.lang.String,java.lang.String)"},"keyword":"When "},{"result":{"duration":570180000,"status":"passed"},"line":156,"name":"I type 1000 characters into \"Option 1\" option field of \"Q1\"","match":{"arguments":[{"val":"1000","offset":7},{"val":"\"Option 1\"","offset":28},{"val":"\"Q1\"","offset":55}],"location":"definitions.SingleChoiceOptionStepDefs.iTypeCharactersIntoOptionFieldOf(int,java.lang.String,java.lang.String)"},"keyword":"And "},{"result":{"duration":38745000,"status":"passed"},"line":157,"name":"I type \"R\" into \"Option 2\" option field of \"Q1\"","match":{"arguments":[{"val":"\"R\"","offset":7},{"val":"\"Option 2\"","offset":16},{"val":"\"Q1\"","offset":43}],"location":"definitions.SingleChoiceOptionStepDefs.iTypeIntoOptionFieldOf(java.lang.String,java.lang.String,java.lang.String)"},"keyword":"And "},{"result":{"duration":21602000,"status":"passed"},"line":158,"name":"I select \"Option 1\" as a correct option in \"Q1\"","match":{"arguments":[{"val":"\"Option 1\"","offset":9},{"val":"\"Q1\"","offset":43}],"location":"definitions.SingleChoiceOptionStepDefs.iSelectAsACorrectOptionIn(java.lang.String,java.lang.String)"},"keyword":"And "},{"result":{"duration":21752000,"status":"passed"},"line":159,"name":"I click \"Save\" button","match":{"arguments":[{"val":"\"Save\"","offset":8}],"location":"definitions.SingleChoiceOptionStepDefs.iClickButton(java.lang.String)"},"keyword":"And "},{"result":{"duration":1005167000,"status":"passed"},"line":160,"name":"I wait for 1 sec","match":{"arguments":[{"val":"1","offset":11}],"location":"definitions.SingleChoiceOptionStepDefs.iWaitForSec(int)"},"keyword":"And "},{"result":{"duration":103892000,"status":"passed"},"line":161,"name":"\"Title#\" is displayed on the list of quizzes","match":{"arguments":[{"val":"\"Title#\"","offset":0}],"location":"definitions.SingleChoiceOptionStepDefs.isDisplayedOnTheListOfQuizzes(java.lang.String)"},"keyword":"Then "},{"result":{"duration":30124000,"status":"passed"},"line":162,"name":"I click on the quiz \"Title#\"","match":{"arguments":[{"val":"\"Title#\"","offset":20}],"location":"definitions.SingleChoiceOptionStepDefs.iClickOnTheQuiz(java.lang.String)"},"keyword":"And "},{"result":{"duration":2001366000,"status":"passed"},"line":163,"name":"I wait for 2 sec","match":{"arguments":[{"val":"2","offset":11}],"location":"definitions.SingleChoiceOptionStepDefs.iWaitForSec(int)"},"keyword":"And "},{"result":{"duration":61734000,"status":"passed"},"line":164,"name":"I \"Preview\" the quiz \"Title#\"","match":{"arguments":[{"val":"\"Preview\"","offset":2},{"val":"\"Title#\"","offset":21}],"location":"definitions.SingleChoiceOptionStepDefs.iTheQuiz(java.lang.String,java.lang.String)"},"keyword":"And "},{"result":{"duration":18738000,"status":"passed"},"line":165,"name":"Option 1 should contain 1000 characters","match":{"arguments":[{"val":"1","offset":7},{"val":"1000","offset":24}],"location":"definitions.SingleChoiceOptionStepDefs.optionShouldContainCharacters(int,int)"},"keyword":"Then "},{"result":{"duration":1004967000,"status":"passed"},"line":166,"name":"I wait for 1 sec","match":{"arguments":[{"val":"1","offset":11}],"location":"definitions.SingleChoiceOptionStepDefs.iWaitForSec(int)"},"keyword":"And "},{"result":{"duration":42254000,"status":"passed"},"line":167,"name":"I click \"Close\" button","match":{"arguments":[{"val":"\"Close\"","offset":8}],"location":"definitions.SingleChoiceOptionStepDefs.iClickButton(java.lang.String)"},"keyword":"And "},{"result":{"duration":1005179000,"status":"passed"},"line":168,"name":"I wait for 1 sec","match":{"arguments":[{"val":"1","offset":11}],"location":"definitions.SingleChoiceOptionStepDefs.iWaitForSec(int)"},"keyword":"And "},{"result":{"duration":73949000,"status":"passed"},"line":169,"name":"I click delete \"Title#\" quiz","match":{"arguments":[{"val":"\"Title#\"","offset":15}],"location":"definitions.SingleChoiceOptionStepDefs.iClickDeleteQuiz(java.lang.String)"},"keyword":"And "}],"tags":[{"name":"@options"},{"name":"@options9"}]}],"name":"Single Choice Question - options","description":"","id":"single-choice-question---options","keyword":"Feature","uri":"file:src/test/resources/features/singleChoiceOption_larissa.feature","tags":[{"name":"@options","type":"Tag","location":{"line":1,"column":1}}]}]